{
  "week": 2,
  "title": "🗓 Неделя 2. Эффективная коммуникация",
  "welcome_message": "«Привет, снова рад вас видеть! 🫂 \nНа этой неделе мы попробуем новые способы общения. Будем делиться своими чувствами простыми словами и слушать друг друга так, чтобы становиться ещё ближе».",
  "questions": "Упражнение:\n 1. Выберите ситуацию, вызвавшую эмоции.\n 2. Партнёр А: «Я чувствую [эмоция], когда [ситуация], потому что [пояснение]».\n 3. Партнёр B пересказывает услышанное и добавляет свои чувства.\n 4. Поменяйтесь ролями.",
  "tips": "Подсказки:\n • «Говорите о себе, а не обвиняйте».\n • «Слушайте внимательно и пересказывайте, что услышали».",
  "insights": "",
  "joint_questions": "Вопросы для обсуждения в конце недели:\n • Что было трудно сказать или услышать?\n • Какие новые ощущения появились?\n • Как изменилось восприятие партнёра?",
  "diary_instructions": "Что делать в дневнике:\nКаждый день фиксируйте маленькие успехи в общении:\n • «Сегодня я сказал(а) о своих чувствах так…»\n • «Сегодня я услышал(а) партнёра и понял(а)…»"
}